halftones/__init__.py
halftones/halftones.py
halftones-0.1.1.dist-info/LICENSE
halftones-0.1.1.dist-info/METADATA
halftones-0.1.1.dist-info/WHEEL
halftones-0.1.1.dist-info/top_level.txt
halftones-0.1.1.dist-info/RECORD
