Metadata-Version: 2.1
Name: halftones
Version: 0.1.1
Summary: Python package for processing and creating halftone images
Home-page: https://github.com/eotles/halftones_pkg
Author: Erkin Ötleş
Author-email: hi@eotles.com
License-File: LICENSE
Requires-Dist: opencv-python
Requires-Dist: matplotlib
Requires-Dist: numpy
Requires-Dist: Pillow
